zacrostools/__init__.py
zacrostools/analysis_functions.py
zacrostools/energetics_input.py
zacrostools/input_functions.py
zacrostools/kmc_model.py
zacrostools/kmc_output.py
zacrostools/lattice_input.py
zacrostools/mechanism_input.py
zacrostools/read_functions.py
zacrostools-0.4b0.dist-info/LICENSE.txt
zacrostools-0.4b0.dist-info/METADATA
zacrostools-0.4b0.dist-info/WHEEL
zacrostools-0.4b0.dist-info/top_level.txt
zacrostools-0.4b0.dist-info/RECORD
