Metadata-Version: 2.1
Name: zacrostools
Version: 0.4b0
Summary: A collective of tools for the preparation of input files for ZACROS
Home-page: https://github.com/hprats/ZacrosTools
Download-URL: https://github.com/hprats/ZacrosTools/archive/refs/tags/v0.4-beta.tar.gz
Author: Hector Prats
Author-email: hpratsgarcia@gmail.com
Keywords: python,chemistry,KMC,ZACROS
License-File: LICENSE.txt
Requires-Dist: pandas
Requires-Dist: scipy
